setup.py
dai/MeteorClient.py
dai/MeteorFiles.py
dai/__init__.py
dai/device_query.py
dai/dummytask.py
dai/imagePreprocessing.py
dai/imageUtils.py
dai/kerasUtils.py
dai/taskProcessors.py
dai/utils.py
dai/worker.py
dai.egg-info/PKG-INFO
dai.egg-info/SOURCES.txt
dai.egg-info/dependency_links.txt
dai.egg-info/not-zip-safe
dai.egg-info/requires.txt
dai.egg-info/top_level.txt