Metadata-Version: 1.0
Name: dai
Version: 0.3.62
Summary: python worker for distributedAI
Home-page: http://github.com/oeway/distributedAI
Author: Wei OUYANG
Author-email: wei.ouyang@cri-paris.org
License: MIT
Platform: UNKNOWN
